aoc_colab_template/__init__.py
aoc_colab_template/template_generator.py
aoc_colab_template-0.1.9.dist-info/LICENSE
aoc_colab_template-0.1.9.dist-info/METADATA
aoc_colab_template-0.1.9.dist-info/WHEEL
aoc_colab_template-0.1.9.dist-info/top_level.txt
aoc_colab_template-0.1.9.dist-info/RECORD
