Metadata-Version: 2.2
Name: aoc-colab-template
Version: 0.1.9
Summary: A template generator for Advent of Code solutions in Google Colab
Home-page: https://github.com/averma12/advent_of_code-colab-template
Author: Abhinav Verma
Author-email: verma.abhinav275l@gmail.com
Classifier: Programming Language :: Python :: 3
Classifier: License :: OSI Approved :: MIT License
Classifier: Operating System :: OS Independent
Requires-Python: >=3.7
License-File: LICENSE
Requires-Dist: ipython
Requires-Dist: advent-of-code-data
Dynamic: author
Dynamic: author-email
Dynamic: classifier
Dynamic: description
Dynamic: description-content-type
Dynamic: home-page
Dynamic: requires-dist
Dynamic: requires-python
Dynamic: summary
